gllm_generation/__init__.pyi
gllm_generation/reference_formatter/__init__.pyi
gllm_generation/reference_formatter/lm_based_reference_formatter.pyi
gllm_generation/reference_formatter/reference_formatter.pyi
gllm_generation/reference_formatter/similarity_based_reference_formatter.pyi
gllm_generation/response_synthesizer/__init__.pyi
gllm_generation/response_synthesizer/response_synthesizer.pyi
gllm_generation/response_synthesizer/static_list_response_synthesizer.pyi
gllm_generation/response_synthesizer/stuff_response_synthesizer.pyi
gllm_generation.build/.gitignore
gllm_generation.cpython-312-darwin.so
gllm_generation.pyi
gllm_generation_binary-0.2.11.dist-info/METADATA
gllm_generation_binary-0.2.11.dist-info/WHEEL
gllm_generation_binary-0.2.11.dist-info/RECORD
