Metadata-Version: 2.1
Name: gllm-generation-binary
Version: 0.2.11
Summary: A library containing generation related components in Gen AI applications.
Author: Henry Wicaksono
Author-email: henry.wicaksono@gdplabs.id
Requires-Python: >=3.11,<3.13
Classifier: Programming Language :: Python :: 3
Classifier: Programming Language :: Python :: 3.11
Classifier: Programming Language :: Python :: 3.12
Requires-Dist: gllm-core-binary
Requires-Dist: gllm-inference-binary
Requires-Dist: libmagic (>=1.0,<2.0) ; sys_platform == "win32"
Requires-Dist: python-magic-bin (>=0.4.14,<0.5.0) ; sys_platform == "win32"
